doitlater/__init__.py
doitlater/later.py
doitlater-0.1.2.dist-info/LICENSE
doitlater-0.1.2.dist-info/WHEEL
doitlater-0.1.2.dist-info/METADATA
doitlater-0.1.2.dist-info/RECORD
