Metadata-Version: 2.1
Name: doitlater
Version: 0.1.2
Summary: When you have to do something... later.
Home-page: https://github.com/evalkaz/doitlater
License: MIT
Keywords: scheduling,later
Author: Evaldas Kazlauskis
Author-email: evaldas@evalkaz.com
Requires-Python: >=3.4,<4.0
Classifier: License :: OSI Approved :: MIT License
Classifier: Programming Language :: Python :: 3
Classifier: Programming Language :: Python :: 3.4
Classifier: Programming Language :: Python :: 3.5
Classifier: Programming Language :: Python :: 3.6
Classifier: Programming Language :: Python :: 3.7
Classifier: Programming Language :: Python :: 3.8
Project-URL: Repository, https://github.com/evalkaz/doitlater
